omnicom.pyi
omnicom.cpython-311-darwin.so
NES/ppu.cpp
NES/mapper.cpp
NES/.DS_Store
NES/rom.h
NES/mapper.h
NES/controller.h
NES/ppu.h
NES/rom.cpp
NES/cpu.h
NES/apu.h
NES/controller.cpp
NES/cpu_helper.cpp
NES/apu.cpp
NES/cpu.cpp
SNES/test_map.py
omnicom-0.3.8.dist-info/RECORD
omnicom-0.3.8.dist-info/WHEEL
omnicom-0.3.8.dist-info/top_level.txt
omnicom-0.3.8.dist-info/METADATA
