Metadata-Version: 2.1
Name: omnicom
Version: 0.3.8
Summary: A python module for a multisystem (currently only NES) emulator
Author: Andrew Ogundimu
